causalimpact/__init__.py
causalimpact/causalimpact_lib.py
causalimpact/data.py
causalimpact/indices.py
causalimpact/plot.py
causalimpact/posterior_processing.py
causalimpact/standardize.py
causalimpact/summary.py
tfp_causalimpact-0.2.0.dist-info/LICENSE
tfp_causalimpact-0.2.0.dist-info/WHEEL
tfp_causalimpact-0.2.0.dist-info/METADATA
tfp_causalimpact-0.2.0.dist-info/RECORD
