Metadata-Version: 2.1
Name: tfp-causalimpact
Version: 0.2.0
Summary: Inferring causal effects using Bayesian Structural Time-Series models
Keywords: 
Author-email: TFP CausalImpact Authors <no-reply@google.com>
Requires-Python: >=3.8
Classifier: Programming Language :: Python :: 3
Classifier: Programming Language :: Python :: 3 :: Only
Classifier: License :: OSI Approved :: Apache Software License
Classifier: Intended Audience :: Science/Research
Requires-Dist: Jinja2
Requires-Dist: altair
Requires-Dist: numpy
Requires-Dist: pandas
Requires-Dist: tensorflow
Requires-Dist: tensorflow-probability
Requires-Dist: absl-py ; extra == "dev"
Requires-Dist: pylint>=2.6.0 ; extra == "dev"
Requires-Dist: pyink ; extra == "dev"
Requires-Dist: pytest ; extra == "dev"
Requires-Dist: pytest-xdist ; extra == "dev"
Requires-Dist: statsmodels ; extra == "dev"
Project-URL: homepage, https://github.com/google/tfp-causalimpact
Project-URL: repository, https://github.com/google/tfp-causalimpact
Provides-Extra: dev
